vaknl_content/__init__.py
vaknl_content/Acco/__init__.py
vaknl_content/Image/__init__.py
vaknl_content/Room/__init__.py
vaknl_content-0.0.2.dist-info/LICENSE
vaknl_content-0.0.2.dist-info/METADATA
vaknl_content-0.0.2.dist-info/WHEEL
vaknl_content-0.0.2.dist-info/top_level.txt
vaknl_content-0.0.2.dist-info/RECORD
