Metadata-Version: 2.1
Name: vaknl-content
Version: 0.0.2
Summary: Vakanties.nl pypi package
Home-page: https://github.com/vakantiesnl/vaknl-PyPi.git
Author: Wytze Bruinsma
Author-email: wytze.bruinsma@vakanties.nl
License: UNKNOWN
Keywords: vaknl,pip
Platform: UNKNOWN
Requires-Python: >=3.7
Requires-Dist: Pillow
Requires-Dist: vaknl-gcp
